bibtex2cff/__init__.py
bibtex2cff/cmd.py
bibtex2cff/convert_cff.py
bibtex2cff/definitions.py
bibtex2cff-0.2.1.dist-info/LICENSE
bibtex2cff-0.2.1.dist-info/METADATA
bibtex2cff-0.2.1.dist-info/WHEEL
bibtex2cff-0.2.1.dist-info/entry_points.txt
bibtex2cff-0.2.1.dist-info/RECORD
