Metadata-Version: 2.1
Name: bibtex2cff
Version: 0.2.1
Summary: Converting Bibtex to CITATION.cff fileformat
License: MIT
Keywords: bibtex,cff,citation,citation-file-format
Author: Anselm Hahn
Author-email: anselm.hahn@gmail.com
Requires-Python: >=3.9,<4.0
Classifier: Development Status :: 3 - Alpha
Classifier: Environment :: Console
Classifier: Intended Audience :: Science/Research
Classifier: License :: OSI Approved :: MIT License
Classifier: Operating System :: OS Independent
Classifier: Programming Language :: Python :: 3
Classifier: Programming Language :: Python :: 3.9
Classifier: Programming Language :: Python :: 3.10
Classifier: Programming Language :: Python :: 3.11
Classifier: Topic :: Scientific/Engineering
Classifier: Topic :: Software Development :: Libraries :: Python Modules
Classifier: Topic :: Text Processing :: Markup :: LaTeX
Requires-Dist: bibtexparser (>=1.4.0,<2.0.0)
Requires-Dist: pydantic[email] (>=1.10.7,<2.0.0)
Requires-Dist: pyyaml (>=6.0,<7.0)
